zeusorasis/__init__.py
zeusorasis/process_batch.py
zeusorasis/process_batch_code.py
zeusorasis/process_sightpro.py
zeusorasis/process_sightpro_code.py
zeusorasis-0.2.dist-info/METADATA
zeusorasis-0.2.dist-info/WHEEL
zeusorasis-0.2.dist-info/top_level.txt
zeusorasis-0.2.dist-info/RECORD
