Metadata-Version: 2.1
Name: zeusorasis
Version: 0.2
Summary: Library to detect eye movements
Author: Robinson Gauci
